charming/__init__.py
charming/app.py
charming/cmath.py
charming/color.py
charming/common.py
charming/constants.py
charming/core.py
charming/environment.py
charming/event.py
charming/globals.py
charming/helpers.py
charming/image.py
charming/io.py
charming/shape.py
charming/structure.py
charming/time.py
charming/transform.py
charming/typography.py
charming/utils.py
charming-1.0.0a2.dist-info/LICENSE
charming-1.0.0a2.dist-info/METADATA
charming-1.0.0a2.dist-info/WHEEL
charming-1.0.0a2.dist-info/top_level.txt
charming-1.0.0a2.dist-info/RECORD
