Metadata-Version: 2.1
Name: charming
Version: 1.0.0a2
Summary: A creative coding language based on Processing and Python for creating interactive character terminal art.
Home-page: https://github.com/charming-art/charming
Author: Pearmini
Author-email: pearminipro@gmail.com
Maintainer: Pearmini
Maintainer-email: pearminipro@gmail.com
License: LGPL v2.1
Platform: UNKNOWN
Classifier: Development Status :: 3 - Alpha
Classifier: Environment :: Console
Classifier: Environment :: Console :: Curses
Classifier: Environment :: MacOS X
Classifier: Intended Audience :: Developers
Classifier: Intended Audience :: Education
Classifier: License :: OSI Approved :: GNU Lesser General Public License v2 or later (LGPLv2+)
Classifier: Operating System :: MacOS :: MacOS X
Classifier: Programming Language :: Python :: 3.6
Classifier: Topic :: Artistic Software
Classifier: Topic :: Education
Classifier: Topic :: Multimedia :: Graphics
Classifier: Topic :: Terminals
Requires-Python: >= 3.6
Requires-Dist: pyfiglet (>=0.7.2)
Requires-Dist: Pillow (>=2.7.0)
